<?xml version='1.0' encoding='utf-8'?><m:page id='072ef2e7-a147-4ec8-8dd9-21bb23d26e2e' xmlns='http://www.w3.org/1999/xhtml' title='Page Title' class='layout-atlas layout-atlas-responsive-default' xmlns:m='http://schemas.mendix.com/forms/1.0'><m:layouts><m:layout path='Atlas_UI_Resources/Atlas_Default.layout.xml'></m:layout></m:layouts><m:arguments><m:argument parameterName='dffd4337-01e4-4a5a-b9e2-d101e19c16e3'><div data-mendix-id='5_0' class='mx-layoutgrid mx-layoutgrid-fluid container-fluid mx-name-layoutGrid1'><div class='row'><div class='col-md-12'><div class='mx-name-container17 flexitem'><div data-mendix-id='5_1' data-mendix-type='mxui.widget.StaticImage' data-mendix-props='"friendlyId":"MyFirstModule.ViewRecipe.image9","url":"img/MyFirstModule$food.jpg?636746204101720962","width":"150px","height":"0px","action":{"type":"doNothing","argMap":{},"config":{}}' class='mx-name-image9 img-circle'></div></div><div data-mendix-id='5_2' data-mendix-type='mxui.widget.DataView' data-mendix-props='"friendlyId":"MyFirstModule.ViewRecipe.dataView6","entity":"MyFirstModule.Recipe","schema":"e48d16fa-527d-4f33-99d7-053b1afb2b6e","readOnly":true,"datasource":{"friendlyId":"MyFirstModule.ViewRecipe.dataView6","type":"direct","path":"MyFirstModule.Recipe"}' class='mx-name-dataView6' tabindex='0'></div></div></div></div></m:argument></m:arguments><m:templates><m:template widget-id='5_2' name='content'><div data-mendix-id='5_3' class='form-group mx-name-textArea1'><div data-mendix-id='5_9' data-mendix-type='mxui.widget.ReactWidgetWrapper' data-mendix-props='"widgetTree":[{"widget":"com.mendix.widget.core.Label","widgetId":"5_9","props":{"name":"","class":"control-label","caption":{"$type":"DynamicTextProperty","scope":"5_2","template":{"elements":["Name"],"friendlyId":"MyFirstModule.ViewRecipe."}}}}]'></div><div data-mendix-id='5_10' data-mendix-type='mxui.widget.TextArea' data-mendix-props='"friendlyId":"MyFirstModule.ViewRecipe.textArea1","readOnly":true,"insideFormGroup":true,"attributePath":"MyFirstModule.Recipe/Name","readOnlyStyle":"control","validation":null,"events":{"change":{"type":"doNothing","argMap":{},"config":{}},"focus":{"type":"doNothing","argMap":{},"config":{}},"blur":{"type":"doNothing","argMap":{},"config":{}}},"placeholder":"","rows":0' tabindex='0'></div></div><div data-mendix-id='5_4' class='form-group mx-name-textArea2'><div data-mendix-id='5_11' data-mendix-type='mxui.widget.ReactWidgetWrapper' data-mendix-props='"widgetTree":[{"widget":"com.mendix.widget.core.Label","widgetId":"5_11","props":{"name":"","class":"control-label","caption":{"$type":"DynamicTextProperty","scope":"5_2","template":{"elements":["Description"],"friendlyId":"MyFirstModule.ViewRecipe."}}}}]'></div><div data-mendix-id='5_12' data-mendix-type='mxui.widget.TextArea' data-mendix-props='"friendlyId":"MyFirstModule.ViewRecipe.textArea2","insideFormGroup":true,"attributePath":"MyFirstModule.Recipe/Description","readOnlyStyle":"control","validation":null,"events":{"change":{"type":"doNothing","argMap":{},"config":{}},"focus":{"type":"doNothing","argMap":{},"config":{}},"blur":{"type":"doNothing","argMap":{},"config":{}}},"placeholder":"","rows":0' tabindex='0'></div></div><div data-mendix-id='5_5' class='form-group mx-name-textArea3'><div data-mendix-id='5_13' data-mendix-type='mxui.widget.ReactWidgetWrapper' data-mendix-props='"widgetTree":[{"widget":"com.mendix.widget.core.Label","widgetId":"5_13","props":{"name":"","class":"control-label","caption":{"$type":"DynamicTextProperty","scope":"5_2","template":{"elements":["Ingredients"],"friendlyId":"MyFirstModule.ViewRecipe."}}}}]'></div><div data-mendix-id='5_14' data-mendix-type='mxui.widget.TextArea' data-mendix-props='"friendlyId":"MyFirstModule.ViewRecipe.textArea3","insideFormGroup":true,"attributePath":"MyFirstModule.Recipe/Ingredients","readOnlyStyle":"control","validation":null,"events":{"change":{"type":"doNothing","argMap":{},"config":{}},"focus":{"type":"doNothing","argMap":{},"config":{}},"blur":{"type":"doNothing","argMap":{},"config":{}}},"placeholder":"","rows":0' tabindex='0'></div></div><div data-mendix-id='5_6' class='form-group mx-name-textArea5'><div data-mendix-id='5_15' data-mendix-type='mxui.widget.ReactWidgetWrapper' data-mendix-props='"widgetTree":[{"widget":"com.mendix.widget.core.Label","widgetId":"5_15","props":{"name":"","class":"control-label","caption":{"$type":"DynamicTextProperty","scope":"5_2","template":{"elements":["Steps"],"friendlyId":"MyFirstModule.ViewRecipe."}}}}]'></div><div data-mendix-id='5_16' data-mendix-type='mxui.widget.TextArea' data-mendix-props='"friendlyId":"MyFirstModule.ViewRecipe.textArea5","insideFormGroup":true,"attributePath":"MyFirstModule.Recipe/Steps","readOnlyStyle":"control","validation":null,"events":{"change":{"type":"doNothing","argMap":{},"config":{}},"focus":{"type":"doNothing","argMap":{},"config":{}},"blur":{"type":"doNothing","argMap":{},"config":{}}},"placeholder":"","rows":0' tabindex='0'></div></div><div data-mendix-id='5_7' class='form-group mx-name-textArea4'><div data-mendix-id='5_17' data-mendix-type='mxui.widget.ReactWidgetWrapper' data-mendix-props='"widgetTree":[{"widget":"com.mendix.widget.core.Label","widgetId":"5_17","props":{"name":"","class":"control-label","caption":{"$type":"DynamicTextProperty","scope":"5_2","template":{"elements":["Categories"],"friendlyId":"MyFirstModule.ViewRecipe."}}}}]'></div><div data-mendix-id='5_18' data-mendix-type='mxui.widget.TextArea' data-mendix-props='"friendlyId":"MyFirstModule.ViewRecipe.textArea4","insideFormGroup":true,"attributePath":"MyFirstModule.Recipe/Categories","readOnlyStyle":"control","validation":null,"events":{"change":{"type":"doNothing","argMap":{},"config":{}},"focus":{"type":"doNothing","argMap":{},"config":{}},"blur":{"type":"doNothing","argMap":{},"config":{}}},"placeholder":"","rows":0' tabindex='0'></div></div></m:template><m:template widget-id='5_2' name='footer'><div data-mendix-id='5_8' data-mendix-type='mxui.widget.ReactWidgetWrapper' data-mendix-props='"widgetTree":[{"widget":"com.mendix.widget.core.ActionButton","widgetId":"5_8","props":{"name":"actionButton2","class":"mx-name-actionButton2","id":"5_8","style":{},"renderType":"button","buttonClass":"btn-primary","caption":{"$type":"DynamicTextProperty","scope":"5_2","template":{"elements":["Back"],"friendlyId":"MyFirstModule.ViewRecipe.actionButton2"}},"tooltip":{"$type":"DynamicTextProperty","template":{"elements":[""]}},"icon":null,"action":{"$type":"ActionProperty","action":{"type":"cancelChanges","argMap":{},"config":{"closePage":true}},"abortOnServerValidation":true},"disabledDuringAction":true}}]'></div></m:template></m:templates></m:page>